{
    "key": "group_6441154c8b92d",
    "title": "404 Error",
    "fields": [
        {
            "key": "field_644115597c74d",
            "label": "Error content",
            "name": "error_content",
            "aria-label": "",
            "type": "repeater",
            "instructions": "",
            "required": 0,
            "conditional_logic": 0,
            "wrapper": {
                "width": "",
                "class": "",
                "id": ""
            },
            "collapsed": "",
            "min": 0,
            "max": 3,
            "layout": "block",
            "button_label": "New row",
            "rows_per_page": 20,
            "repeatable": true,
            "sub_fields": [
                {
                    "key": "field_644115867c74e",
                    "label": "Icon",
                    "name": "icon",
                    "aria-label": "",
                    "type": "component_field",
                    "instructions": "",
                    "required": 0,
                    "conditional_logic": 0,
                    "wrapper": {
                        "width": "",
                        "class": "",
                        "id": ""
                    },
                    "field_group_key": "group_64414885d353d",
                    "repeatable": true,
                    "layout": "block",
                    "button_label": "",
                    "appearances": "",
                    "min": null,
                    "max": null,
                    "collapsed": "",
                    "sub_fields": [],
                    "parent_repeater": "field_644115597c74d"
                },
                {
                    "key": "field_644115997c74f",
                    "label": "Title",
                    "name": "title",
                    "aria-label": "",
                    "type": "text",
                    "instructions": "",
                    "required": 1,
                    "conditional_logic": 0,
                    "wrapper": {
                        "width": "",
                        "class": "",
                        "id": ""
                    },
                    "default_value": "",
                    "placeholder": "",
                    "prepend": "",
                    "append": "",
                    "maxlength": "",
                    "repeatable": true,
                    "parent_repeater": "field_644115597c74d"
                },
                {
                    "key": "field_644115a67c750",
                    "label": "Text",
                    "name": "text",
                    "aria-label": "",
                    "type": "textarea",
                    "instructions": "",
                    "required": 0,
                    "conditional_logic": 0,
                    "wrapper": {
                        "width": "",
                        "class": "",
                        "id": ""
                    },
                    "default_value": "",
                    "placeholder": "",
                    "maxlength": "",
                    "rows": "",
                    "new_lines": "",
                    "repeatable": true,
                    "acfe_textarea_code": 0,
                    "parent_repeater": "field_644115597c74d"
                },
                {
                    "key": "field_644115b07c751",
                    "label": "Link",
                    "name": "link",
                    "aria-label": "",
                    "type": "link",
                    "instructions": "",
                    "required": 0,
                    "conditional_logic": 0,
                    "wrapper": {
                        "width": "",
                        "class": "",
                        "id": ""
                    },
                    "return_format": "array",
                    "repeatable": true,
                    "parent_repeater": "field_644115597c74d"
                }
            ],
            "acfe_repeater_stylised_button": 0
        }
    ],
    "location": [
        [
            {
                "param": "options_page",
                "operator": "==",
                "value": "acf-options-%db%b4%db%b0%db%b4"
            }
        ]
    ],
    "menu_order": 0,
    "position": "normal",
    "style": "default",
    "label_placement": "top",
    "instruction_placement": "label",
    "hide_on_screen": "",
    "active": true,
    "description": "",
    "show_in_rest": 0,
    "acfe_display_title": "",
    "acfe_autosync": [
        "json"
    ],
    "is_acf_component": 0,
    "acfe_form": 0,
    "acf_component_defaults": {
        "repeatable": "0",
        "min": "",
        "max": "",
        "layout": "block",
        "button_label": "",
        "appearances": ""
    },
    "acfe_meta": "",
    "acfe_note": "",
    "modified": 1692445421
}
